purpletrader/__init__.py
purpletrader/client.py
purpletrader/errors.py
purpletrader/types.py
purpletrader-0.1.1.dist-info/METADATA
purpletrader-0.1.1.dist-info/WHEEL
purpletrader-0.1.1.dist-info/licenses/LICENSE
purpletrader-0.1.1.dist-info/RECORD
