Metadata-Version: 2.4
Name: purpletrader
Version: 0.1.1
Summary: A lightweight Python client for the Amherst College Quant Club Live Trading Engine.
Project-URL: Homepage, https://github.com/ACquantclub/purpletrader
License: MIT
License-File: LICENSE
Keywords: api,client,http,trading
Classifier: License :: OSI Approved :: MIT License
Classifier: Operating System :: OS Independent
Classifier: Programming Language :: Python :: 3
Classifier: Programming Language :: Python :: 3 :: Only
Requires-Python: >=3.9
Requires-Dist: requests>=2.31.0
Provides-Extra: bots
Requires-Dist: pyyaml>=6.0.1; extra == 'bots'
